[
  {
    "id": "villa-for-sale-ras-al-khaimah-mina-al-arab-marbella-2Pv7rqWq7Y8",
    "url": "https://www.propertyfinder.aehttps://www.propertyfinder.ae/en/plp/buy/villa-for-sale-ras-al-khaimah-mina-al-arab-marbella-2Pv7rqWq7Y8.html",
    "title": "~ 12K Mortgage Cashback",
    "type": "",
    "location": "",
    "price": 5276992,
    "beds": 0,
    "baths": 0,
    "sqft": 0,
    "price_sqft": 0,
    "old_price": 527699212,
    "new_price": 5276992,
    "drop_aed": 522422220,
    "drop_pct": 99.0,
    "detected_at": "2026-03-25T17:36:48.280812Z"
  },
  {
    "id": "villa-for-sale-ras-al-khaimah-mina-al-arab-marbella-2Pv7gNT65g1",
    "url": "https://www.propertyfinder.aehttps://www.propertyfinder.ae/en/plp/buy/villa-for-sale-ras-al-khaimah-mina-al-arab-marbella-2Pv7gNT65g1.html",
    "title": "~ 12K Mortgage Cashback",
    "type": "",
    "location": "",
    "price": 5276992,
    "beds": 0,
    "baths": 0,
    "sqft": 0,
    "price_sqft": 0,
    "old_price": 527699212,
    "new_price": 5276992,
    "drop_aed": 522422220,
    "drop_pct": 99.0,
    "detected_at": "2026-03-25T17:36:48.280816Z"
  },
  {
    "id": "villa-for-sale-ras-al-khaimah-mina-al-arab-marbella-marbella-i-villas-16294589",
    "url": "https://www.propertyfinder.aehttps://www.propertyfinder.ae/en/plp/buy/villa-for-sale-ras-al-khaimah-mina-al-arab-marbella-marbella-i-villas-16294589.html",
    "title": "~ 21K Mortgage Cashback",
    "type": "",
    "location": "",
    "price": 10000000,
    "beds": 0,
    "baths": 0,
    "sqft": 0,
    "price_sqft": 0,
    "old_price": 1000000021,
    "new_price": 10000000,
    "drop_aed": 990000021,
    "drop_pct": 99.0,
    "detected_at": "2026-03-25T17:36:48.280834Z"
  },
  {
    "id": "townhouse-for-sale-ras-al-khaimah-mina-al-arab-marbella-marbella-ii-villas-14761034",
    "url": "https://www.propertyfinder.aehttps://www.propertyfinder.ae/en/plp/buy/townhouse-for-sale-ras-al-khaimah-mina-al-arab-marbella-marbella-ii-villas-14761034.html",
    "title": "~ 20K Mortgage Cashback",
    "type": "",
    "location": "",
    "price": 9300000,
    "beds": 0,
    "baths": 0,
    "sqft": 0,
    "price_sqft": 0,
    "old_price": 930000020,
    "new_price": 9300000,
    "drop_aed": 920700020,
    "drop_pct": 99.0,
    "detected_at": "2026-03-25T17:36:48.280847Z"
  },
  {
    "id": "villa-for-sale-ras-al-khaimah-mina-al-arab-marbella-marbella-ii-villas-2PXiwmeH3IW",
    "url": "https://www.propertyfinder.aehttps://www.propertyfinder.ae/en/plp/buy/villa-for-sale-ras-al-khaimah-mina-al-arab-marbella-marbella-ii-villas-2PXiwmeH3IW.html",
    "title": "~ 12K Mortgage Cashback",
    "type": "",
    "location": "",
    "price": 5276992,
    "beds": 0,
    "baths": 0,
    "sqft": 0,
    "price_sqft": 0,
    "old_price": 527699212,
    "new_price": 5276992,
    "drop_aed": 522422220,
    "drop_pct": 99.0,
    "detected_at": "2026-03-25T17:36:48.280866Z"
  },
  {
    "id": "villa-for-sale-ras-al-khaimah-mina-al-arab-marbella-marbella-i-villas-15947145",
    "url": "https://www.propertyfinder.aehttps://www.propertyfinder.ae/en/plp/buy/villa-for-sale-ras-al-khaimah-mina-al-arab-marbella-marbella-i-villas-15947145.html",
    "title": "~ 21K Mortgage Cashback",
    "type": "",
    "location": "",
    "price": 10000000,
    "beds": 0,
    "baths": 0,
    "sqft": 0,
    "price_sqft": 0,
    "old_price": 1000000021,
    "new_price": 10000000,
    "drop_aed": 990000021,
    "drop_pct": 99.0,
    "detected_at": "2026-03-25T17:36:48.280880Z"
  },
  {
    "id": "villa-for-sale-ras-al-khaimah-mina-al-arab-bermuda-2PUIr62J6vI",
    "url": "https://www.propertyfinder.aehttps://www.propertyfinder.ae/en/plp/buy/villa-for-sale-ras-al-khaimah-mina-al-arab-bermuda-2PUIr62J6vI.html",
    "title": "~ 22K Mortgage Cashback",
    "type": "",
    "location": "",
    "price": 10210000,
    "beds": 0,
    "baths": 0,
    "sqft": 0,
    "price_sqft": 0,
    "old_price": 1021000022,
    "new_price": 10210000,
    "drop_aed": 1010790022,
    "drop_pct": 99.0,
    "detected_at": "2026-03-25T17:36:48.280961Z"
  },
  {
    "id": "villa-for-sale-ras-al-khaimah-mina-al-arab-marbella-16112834",
    "url": "https://www.propertyfinder.aehttps://www.propertyfinder.ae/en/plp/buy/villa-for-sale-ras-al-khaimah-mina-al-arab-marbella-16112834.html",
    "title": "~ 20K Mortgage Cashback",
    "type": "",
    "location": "",
    "price": 9200000,
    "beds": 0,
    "baths": 0,
    "sqft": 0,
    "price_sqft": 0,
    "old_price": 920000020,
    "new_price": 9200000,
    "drop_aed": 910800020,
    "drop_pct": 99.0,
    "detected_at": "2026-03-25T17:36:48.280974Z"
  },
  {
    "id": "townhouse-for-sale-ras-al-khaimah-mina-al-arab-marbella-marbella-i-villas-15953517",
    "url": "https://www.propertyfinder.aehttps://www.propertyfinder.ae/en/plp/buy/townhouse-for-sale-ras-al-khaimah-mina-al-arab-marbella-marbella-i-villas-15953517.html",
    "title": "~ 20K Mortgage Cashback",
    "type": "",
    "location": "",
    "price": 9200000,
    "beds": 0,
    "baths": 0,
    "sqft": 0,
    "price_sqft": 0,
    "old_price": 920000020,
    "new_price": 9200000,
    "drop_aed": 910800020,
    "drop_pct": 99.0,
    "detected_at": "2026-03-25T17:36:48.280980Z"
  },
  {
    "id": "villa-for-sale-ras-al-khaimah-mina-al-arab-marbella-marbella-i-villas-15952815",
    "url": "https://www.propertyfinder.aehttps://www.propertyfinder.ae/en/plp/buy/villa-for-sale-ras-al-khaimah-mina-al-arab-marbella-marbella-i-villas-15952815.html",
    "title": "~ 20K Mortgage Cashback",
    "type": "",
    "location": "",
    "price": 9200000,
    "beds": 0,
    "baths": 0,
    "sqft": 0,
    "price_sqft": 0,
    "old_price": 920000020,
    "new_price": 9200000,
    "drop_aed": 910800020,
    "drop_pct": 99.0,
    "detected_at": "2026-03-25T17:36:48.280983Z"
  },
  {
    "id": "villa-for-sale-ras-al-khaimah-mina-al-arab-marbella-marbella-ii-villas-2Q6lFx5EKSe",
    "url": "https://www.propertyfinder.aehttps://www.propertyfinder.ae/en/plp/buy/villa-for-sale-ras-al-khaimah-mina-al-arab-marbella-marbella-ii-villas-2Q6lFx5EKSe.html",
    "title": "~ 12K Mortgage Cashback",
    "type": "",
    "location": "",
    "price": 5276992,
    "beds": 0,
    "baths": 0,
    "sqft": 0,
    "price_sqft": 0,
    "old_price": 527699212,
    "new_price": 5276992,
    "drop_aed": 522422220,
    "drop_pct": 99.0,
    "detected_at": "2026-03-25T17:36:48.280989Z"
  },
  {
    "id": "villa-for-sale-ras-al-khaimah-mina-al-arab-malibu-2Q50UMyPQOG",
    "url": "https://www.propertyfinder.aehttps://www.propertyfinder.ae/en/plp/buy/villa-for-sale-ras-al-khaimah-mina-al-arab-malibu-2Q50UMyPQOG.html",
    "title": "~ 16K Mortgage Cashback",
    "type": "",
    "location": "",
    "price": 7200000,
    "beds": 0,
    "baths": 0,
    "sqft": 0,
    "price_sqft": 0,
    "old_price": 720000016,
    "new_price": 7200000,
    "drop_aed": 712800016,
    "drop_pct": 99.0,
    "detected_at": "2026-03-25T17:36:48.281000Z"
  },
  {
    "id": "townhouse-for-sale-ras-al-khaimah-mina-al-arab-marbella-marbella-ii-villas-2PecBbzQ4v2",
    "url": "https://www.propertyfinder.aehttps://www.propertyfinder.ae/en/plp/buy/townhouse-for-sale-ras-al-khaimah-mina-al-arab-marbella-marbella-ii-villas-2PecBbzQ4v2.html",
    "title": "~ 12K Mortgage Cashback",
    "type": "",
    "location": "",
    "price": 5276992,
    "beds": 0,
    "baths": 0,
    "sqft": 0,
    "price_sqft": 0,
    "old_price": 527699212,
    "new_price": 5276992,
    "drop_aed": 522422220,
    "drop_pct": 99.0,
    "detected_at": "2026-03-25T17:36:48.281012Z"
  },
  {
    "id": "villa-for-sale-ras-al-khaimah-mina-al-arab-bermuda-2PeXb6uprkW",
    "url": "https://www.propertyfinder.aehttps://www.propertyfinder.ae/en/plp/buy/villa-for-sale-ras-al-khaimah-mina-al-arab-bermuda-2PeXb6uprkW.html",
    "title": "~ 23K Mortgage Cashback",
    "type": "",
    "location": "",
    "price": 10500000,
    "beds": 0,
    "baths": 0,
    "sqft": 0,
    "price_sqft": 0,
    "old_price": 1050000023,
    "new_price": 10500000,
    "drop_aed": 1039500023,
    "drop_pct": 99.0,
    "detected_at": "2026-03-25T17:36:48.281015Z"
  },
  {
    "id": "villa-for-sale-ras-al-khaimah-mina-al-arab-marbella-marbella-i-villas-16175373",
    "url": "https://www.propertyfinder.aehttps://www.propertyfinder.ae/en/plp/buy/villa-for-sale-ras-al-khaimah-mina-al-arab-marbella-marbella-i-villas-16175373.html",
    "title": "~ 19K Mortgage Cashback",
    "type": "",
    "location": "",
    "price": 8999999,
    "beds": 0,
    "baths": 0,
    "sqft": 0,
    "price_sqft": 0,
    "old_price": 899999919,
    "new_price": 8999999,
    "drop_aed": 890999920,
    "drop_pct": 99.0,
    "detected_at": "2026-03-25T17:36:48.281031Z"
  },
  {
    "id": "villa-for-sale-ras-al-khaimah-mina-al-arab-bermuda-16121740",
    "url": "https://www.propertyfinder.aehttps://www.propertyfinder.ae/en/plp/buy/villa-for-sale-ras-al-khaimah-mina-al-arab-bermuda-16121740.html",
    "title": "~ 24K Mortgage Cashback",
    "type": "",
    "location": "",
    "price": 11000000,
    "beds": 0,
    "baths": 0,
    "sqft": 0,
    "price_sqft": 0,
    "old_price": 1100000024,
    "new_price": 11000000,
    "drop_aed": 1089000024,
    "drop_pct": 99.0,
    "detected_at": "2026-03-25T17:36:48.281038Z"
  },
  {
    "id": "villa-for-sale-ras-al-khaimah-mina-al-arab-malibu-2Q6PAgiQ45A",
    "url": "https://www.propertyfinder.aehttps://www.propertyfinder.ae/en/plp/buy/villa-for-sale-ras-al-khaimah-mina-al-arab-malibu-2Q6PAgiQ45A.html",
    "title": "~ 12K Mortgage Cashback",
    "type": "",
    "location": "",
    "price": 5700000,
    "beds": 0,
    "baths": 0,
    "sqft": 0,
    "price_sqft": 0,
    "old_price": 570000012,
    "new_price": 5700000,
    "drop_aed": 564300012,
    "drop_pct": 99.0,
    "detected_at": "2026-03-25T17:36:48.281061Z"
  },
  {
    "id": "villa-for-sale-ras-al-khaimah-mina-al-arab-malibu-2PUTcMg0FWa",
    "url": "https://www.propertyfinder.aehttps://www.propertyfinder.ae/en/plp/buy/villa-for-sale-ras-al-khaimah-mina-al-arab-malibu-2PUTcMg0FWa.html",
    "title": "~ 12K Mortgage Cashback",
    "type": "",
    "location": "",
    "price": 5270000,
    "beds": 0,
    "baths": 0,
    "sqft": 0,
    "price_sqft": 0,
    "old_price": 527000012,
    "new_price": 5270000,
    "drop_aed": 521730012,
    "drop_pct": 99.0,
    "detected_at": "2026-03-25T17:36:48.281068Z"
  },
  {
    "id": "villa-for-sale-ras-al-khaimah-mina-al-arab-marbella-marbella-ii-villas-2PUSMmlPZWC",
    "url": "https://www.propertyfinder.aehttps://www.propertyfinder.ae/en/plp/buy/villa-for-sale-ras-al-khaimah-mina-al-arab-marbella-marbella-ii-villas-2PUSMmlPZWC.html",
    "title": "~ 13K Mortgage Cashback",
    "type": "",
    "location": "",
    "price": 5750000,
    "beds": 0,
    "baths": 0,
    "sqft": 0,
    "price_sqft": 0,
    "old_price": 575000013,
    "new_price": 5750000,
    "drop_aed": 569250013,
    "drop_pct": 99.0,
    "detected_at": "2026-03-25T17:36:48.281075Z"
  },
  {
    "id": "villa-for-sale-ras-al-khaimah-mina-al-arab-marbella-marbella-ii-villas-2PUS17uYNqy",
    "url": "https://www.propertyfinder.aehttps://www.propertyfinder.ae/en/plp/buy/villa-for-sale-ras-al-khaimah-mina-al-arab-marbella-marbella-ii-villas-2PUS17uYNqy.html",
    "title": "~ 22K Mortgage Cashback",
    "type": "",
    "location": "",
    "price": 10200000,
    "beds": 0,
    "baths": 0,
    "sqft": 0,
    "price_sqft": 0,
    "old_price": 1020000022,
    "new_price": 10200000,
    "drop_aed": 1009800022,
    "drop_pct": 99.0,
    "detected_at": "2026-03-25T17:36:48.281078Z"
  },
  {
    "id": "villa-for-sale-ras-al-khaimah-mina-al-arab-marbella-marbella-ii-villas-2PURzpGCeUS",
    "url": "https://www.propertyfinder.aehttps://www.propertyfinder.ae/en/plp/buy/villa-for-sale-ras-al-khaimah-mina-al-arab-marbella-marbella-ii-villas-2PURzpGCeUS.html",
    "title": "~ 14K Mortgage Cashback",
    "type": "",
    "location": "",
    "price": 6300000,
    "beds": 0,
    "baths": 0,
    "sqft": 0,
    "price_sqft": 0,
    "old_price": 630000014,
    "new_price": 6300000,
    "drop_aed": 623700014,
    "drop_pct": 99.0,
    "detected_at": "2026-03-25T17:36:48.281081Z"
  },
  {
    "id": "villa-for-sale-ras-al-khaimah-mina-al-arab-marbella-marbella-i-villas-16282319",
    "url": "https://www.propertyfinder.aehttps://www.propertyfinder.ae/en/plp/buy/villa-for-sale-ras-al-khaimah-mina-al-arab-marbella-marbella-i-villas-16282319.html",
    "title": "~ 20K Mortgage Cashback",
    "type": "",
    "location": "",
    "price": 9200000,
    "beds": 0,
    "baths": 0,
    "sqft": 0,
    "price_sqft": 0,
    "old_price": 920000020,
    "new_price": 9200000,
    "drop_aed": 910800020,
    "drop_pct": 99.0,
    "detected_at": "2026-03-25T17:36:48.281095Z"
  },
  {
    "id": "apartment-for-sale-ras-al-khaimah-mina-al-arab-hayat-island-bay-residences-16306300",
    "url": "https://www.propertyfinder.aehttps://www.propertyfinder.ae/en/plp/buy/apartment-for-sale-ras-al-khaimah-mina-al-arab-hayat-island-bay-residences-16306300.html",
    "title": "~ 15K Mortgage Cashback",
    "type": "",
    "location": "",
    "price": 7120000,
    "beds": 0,
    "baths": 0,
    "sqft": 0,
    "price_sqft": 0,
    "old_price": 712000015,
    "new_price": 7120000,
    "drop_aed": 704880015,
    "drop_pct": 99.0,
    "detected_at": "2026-03-25T17:36:48.281144Z"
  },
  {
    "id": "apartment-for-sale-ras-al-khaimah-mina-al-arab-hayat-island-bay-residences-15865024",
    "url": "https://www.propertyfinder.aehttps://www.propertyfinder.ae/en/plp/buy/apartment-for-sale-ras-al-khaimah-mina-al-arab-hayat-island-bay-residences-15865024.html",
    "title": "~ 15K Mortgage Cashback",
    "type": "",
    "location": "",
    "price": 7120000,
    "beds": 0,
    "baths": 0,
    "sqft": 0,
    "price_sqft": 0,
    "old_price": 712000015,
    "new_price": 7120000,
    "drop_aed": 704880015,
    "drop_pct": 99.0,
    "detected_at": "2026-03-25T17:36:48.281163Z"
  },
  {
    "id": "townhouse-for-sale-ras-al-khaimah-mina-al-arab-hayat-island-bay-residences-15903412",
    "url": "https://www.propertyfinder.aehttps://www.propertyfinder.ae/en/plp/buy/townhouse-for-sale-ras-al-khaimah-mina-al-arab-hayat-island-bay-residences-15903412.html",
    "title": "~ 15K Mortgage Cashback",
    "type": "",
    "location": "",
    "price": 7120000,
    "beds": 0,
    "baths": 0,
    "sqft": 0,
    "price_sqft": 0,
    "old_price": 712000015,
    "new_price": 7120000,
    "drop_aed": 704880015,
    "drop_pct": 99.0,
    "detected_at": "2026-03-25T17:36:48.281236Z"
  },
  {
    "id": "townhouse-for-sale-ras-al-khaimah-mina-al-arab-hayat-island-bay-residences-15015109",
    "url": "https://www.propertyfinder.aehttps://www.propertyfinder.ae/en/plp/buy/townhouse-for-sale-ras-al-khaimah-mina-al-arab-hayat-island-bay-residences-15015109.html",
    "title": "~ 17K Mortgage Cashback",
    "type": "",
    "location": "",
    "price": 7900000,
    "beds": 0,
    "baths": 0,
    "sqft": 0,
    "price_sqft": 0,
    "old_price": 790000017,
    "new_price": 7900000,
    "drop_aed": 782100017,
    "drop_pct": 99.0,
    "detected_at": "2026-03-25T17:36:48.281242Z"
  },
  {
    "id": "villa-for-sale-ras-al-khaimah-mina-al-arab-marbella-marbella-i-villas-2Pz0xvZ77cO",
    "url": "https://www.propertyfinder.aehttps://www.propertyfinder.ae/en/plp/buy/villa-for-sale-ras-al-khaimah-mina-al-arab-marbella-marbella-i-villas-2Pz0xvZ77cO.html",
    "title": "~ 18K Mortgage Cashback",
    "type": "",
    "location": "",
    "price": 8500000,
    "beds": 0,
    "baths": 0,
    "sqft": 0,
    "price_sqft": 0,
    "old_price": 850000018,
    "new_price": 8500000,
    "drop_aed": 841500018,
    "drop_pct": 99.0,
    "detected_at": "2026-03-25T17:36:48.281265Z"
  },
  {
    "id": "villa-for-sale-ras-al-khaimah-mina-al-arab-anantara-mina-2PZg0l3Obiq",
    "url": "https://www.propertyfinder.aehttps://www.propertyfinder.ae/en/plp/buy/villa-for-sale-ras-al-khaimah-mina-al-arab-anantara-mina-2PZg0l3Obiq.html",
    "title": "Exclusive Resale | 20/80 Payment Plan | Villa",
    "type": "",
    "location": "",
    "price": 19500000,
    "beds": 0,
    "baths": 0,
    "sqft": 0,
    "price_sqft": 0,
    "old_price": 1950000041,
    "new_price": 19500000,
    "drop_aed": 1930500041,
    "drop_pct": 99.0,
    "detected_at": "2026-03-25T17:36:48.281280Z"
  },
  {
    "id": "duplex-for-sale-ras-al-khaimah-mina-al-arab-anantara-mina-2Q6VXwXIFma",
    "url": "https://www.propertyfinder.aehttps://www.propertyfinder.ae/en/plp/buy/duplex-for-sale-ras-al-khaimah-mina-al-arab-anantara-mina-2Q6VXwXIFma.html",
    "title": "~ 36K Mortgage Cashback",
    "type": "",
    "location": "",
    "price": 16761000,
    "beds": 0,
    "baths": 0,
    "sqft": 0,
    "price_sqft": 0,
    "old_price": 1676100036,
    "new_price": 16761000,
    "drop_aed": 1659339036,
    "drop_pct": 99.0,
    "detected_at": "2026-03-25T17:36:48.281288Z"
  },
  {
    "id": "villa-for-sale-ras-al-khaimah-mina-al-arab-marbella-marbella-ii-villas-2PyNFATMaUC",
    "url": "https://www.propertyfinder.aehttps://www.propertyfinder.ae/en/plp/buy/villa-for-sale-ras-al-khaimah-mina-al-arab-marbella-marbella-ii-villas-2PyNFATMaUC.html",
    "title": "~ 12K Mortgage Cashback",
    "type": "",
    "location": "",
    "price": 5347000,
    "beds": 0,
    "baths": 0,
    "sqft": 0,
    "price_sqft": 0,
    "old_price": 534700012,
    "new_price": 5347000,
    "drop_aed": 529353012,
    "drop_pct": 99.0,
    "detected_at": "2026-03-25T17:36:48.281310Z"
  },
  {
    "id": "villa-for-sale-ras-al-khaimah-mina-al-arab-marbella-marbella-ii-villas-15954154",
    "url": "https://www.propertyfinder.aehttps://www.propertyfinder.ae/en/plp/buy/villa-for-sale-ras-al-khaimah-mina-al-arab-marbella-marbella-ii-villas-15954154.html",
    "title": "~ 12K Mortgage Cashback",
    "type": "",
    "location": "",
    "price": 5276992,
    "beds": 0,
    "baths": 0,
    "sqft": 0,
    "price_sqft": 0,
    "old_price": 527699212,
    "new_price": 5276992,
    "drop_aed": 522422220,
    "drop_pct": 99.0,
    "detected_at": "2026-03-25T17:36:48.281376Z"
  },
  {
    "id": "villa-for-sale-ras-al-khaimah-mina-al-arab-marbella-marbella-ii-villas-15962413",
    "url": "https://www.propertyfinder.aehttps://www.propertyfinder.ae/en/plp/buy/villa-for-sale-ras-al-khaimah-mina-al-arab-marbella-marbella-ii-villas-15962413.html",
    "title": "~ 12K Mortgage Cashback",
    "type": "",
    "location": "",
    "price": 5276992,
    "beds": 0,
    "baths": 0,
    "sqft": 0,
    "price_sqft": 0,
    "old_price": 527699212,
    "new_price": 5276992,
    "drop_aed": 522422220,
    "drop_pct": 99.0,
    "detected_at": "2026-03-25T17:36:48.281449Z"
  },
  {
    "id": "villa-for-sale-ras-al-khaimah-mina-al-arab-marbella-marbella-ii-villas-2Q3HWWHD9Rg",
    "url": "https://www.propertyfinder.aehttps://www.propertyfinder.ae/en/plp/buy/villa-for-sale-ras-al-khaimah-mina-al-arab-marbella-marbella-ii-villas-2Q3HWWHD9Rg.html",
    "title": "~ 13K Mortgage Cashback",
    "type": "",
    "location": "",
    "price": 6000000,
    "beds": 0,
    "baths": 0,
    "sqft": 0,
    "price_sqft": 0,
    "old_price": 600000013,
    "new_price": 6000000,
    "drop_aed": 594000013,
    "drop_pct": 99.0,
    "detected_at": "2026-03-25T17:36:48.281506Z"
  },
  {
    "id": "villa-for-sale-ras-al-khaimah-mina-al-arab-marbella-marbella-i-villas-2Q5igixPed6",
    "url": "https://www.propertyfinder.aehttps://www.propertyfinder.ae/en/plp/buy/villa-for-sale-ras-al-khaimah-mina-al-arab-marbella-marbella-i-villas-2Q5igixPed6.html",
    "title": "~ 24K Mortgage Cashback",
    "type": "",
    "location": "",
    "price": 11000000,
    "beds": 0,
    "baths": 0,
    "sqft": 0,
    "price_sqft": 0,
    "old_price": 1100000024,
    "new_price": 11000000,
    "drop_aed": 1089000024,
    "drop_pct": 99.0,
    "detected_at": "2026-03-25T17:36:48.281666Z"
  },
  {
    "id": "villa-for-sale-ras-al-khaimah-mina-al-arab-marbella-marbella-ii-villas-16102457",
    "url": "https://www.propertyfinder.aehttps://www.propertyfinder.ae/en/plp/buy/villa-for-sale-ras-al-khaimah-mina-al-arab-marbella-marbella-ii-villas-16102457.html",
    "title": "~ 12K Mortgage Cashback",
    "type": "",
    "location": "",
    "price": 5700000,
    "beds": 0,
    "baths": 0,
    "sqft": 0,
    "price_sqft": 0,
    "old_price": 570000012,
    "new_price": 5700000,
    "drop_aed": 564300012,
    "drop_pct": 99.0,
    "detected_at": "2026-03-25T17:36:48.281670Z"
  },
  {
    "id": "apartment-for-sale-ras-al-khaimah-mina-al-arab-bermuda-2PfzTSt8A9w",
    "url": "https://www.propertyfinder.aehttps://www.propertyfinder.ae/en/plp/buy/apartment-for-sale-ras-al-khaimah-mina-al-arab-bermuda-2PfzTSt8A9w.html",
    "title": "~ 12K Mortgage Cashback",
    "type": "",
    "location": "",
    "price": 5500000,
    "beds": 0,
    "baths": 0,
    "sqft": 0,
    "price_sqft": 0,
    "old_price": 550000012,
    "new_price": 5500000,
    "drop_aed": 544500012,
    "drop_pct": 99.0,
    "detected_at": "2026-03-25T17:36:48.281743Z"
  },
  {
    "id": "villa-for-sale-ras-al-khaimah-mina-al-arab-marbella-marbella-i-villas-2Q3n7VjJIPI",
    "url": "https://www.propertyfinder.aehttps://www.propertyfinder.ae/en/plp/buy/villa-for-sale-ras-al-khaimah-mina-al-arab-marbella-marbella-i-villas-2Q3n7VjJIPI.html",
    "title": "~ 24K Mortgage Cashback",
    "type": "",
    "location": "",
    "price": 11000000,
    "beds": 0,
    "baths": 0,
    "sqft": 0,
    "price_sqft": 0,
    "old_price": 1100000024,
    "new_price": 11000000,
    "drop_aed": 1089000024,
    "drop_pct": 99.0,
    "detected_at": "2026-03-25T17:36:48.281770Z"
  },
  {
    "id": "villa-for-sale-ras-al-khaimah-mina-al-arab-marbella-marbella-ii-villas-2PlOyFaeHNA",
    "url": "https://www.propertyfinder.aehttps://www.propertyfinder.ae/en/plp/buy/villa-for-sale-ras-al-khaimah-mina-al-arab-marbella-marbella-ii-villas-2PlOyFaeHNA.html",
    "title": "~ 12K Mortgage Cashback",
    "type": "",
    "location": "",
    "price": 5276000,
    "beds": 0,
    "baths": 0,
    "sqft": 0,
    "price_sqft": 0,
    "old_price": 527600012,
    "new_price": 5276000,
    "drop_aed": 522324012,
    "drop_pct": 99.0,
    "detected_at": "2026-03-25T17:36:48.282050Z"
  },
  {
    "id": "villa-for-sale-ras-al-khaimah-mina-al-arab-bermuda-15939724",
    "url": "https://www.propertyfinder.aehttps://www.propertyfinder.ae/en/plp/buy/villa-for-sale-ras-al-khaimah-mina-al-arab-bermuda-15939724.html",
    "title": "~ 11K Mortgage Cashback",
    "type": "",
    "location": "",
    "price": 5100000,
    "beds": 0,
    "baths": 0,
    "sqft": 0,
    "price_sqft": 0,
    "old_price": 510000011,
    "new_price": 5100000,
    "drop_aed": 504900011,
    "drop_pct": 99.0,
    "detected_at": "2026-03-25T17:36:48.282148Z"
  },
  {
    "id": "villa-for-sale-ras-al-khaimah-mina-al-arab-bermuda-9982279",
    "url": "https://www.propertyfinder.aehttps://www.propertyfinder.ae/en/plp/buy/villa-for-sale-ras-al-khaimah-mina-al-arab-bermuda-9982279.html",
    "title": "~ 14K Mortgage Cashback",
    "type": "",
    "location": "",
    "price": 6500000,
    "beds": 0,
    "baths": 0,
    "sqft": 0,
    "price_sqft": 0,
    "old_price": 650000014,
    "new_price": 6500000,
    "drop_aed": 643500014,
    "drop_pct": 99.0,
    "detected_at": "2026-03-25T17:36:48.282154Z"
  },
  {
    "id": "duplex-for-sale-ras-al-khaimah-mina-al-arab-hayat-island-bay-residences-2PaGBuKibBY",
    "url": "https://www.propertyfinder.aehttps://www.propertyfinder.ae/en/plp/buy/duplex-for-sale-ras-al-khaimah-mina-al-arab-hayat-island-bay-residences-2PaGBuKibBY.html",
    "title": "~ 15K Mortgage Cashback",
    "type": "",
    "location": "",
    "price": 7120000,
    "beds": 0,
    "baths": 0,
    "sqft": 0,
    "price_sqft": 0,
    "old_price": 712000015,
    "new_price": 7120000,
    "drop_aed": 704880015,
    "drop_pct": 99.0,
    "detected_at": "2026-03-25T17:36:48.282159Z"
  },
  {
    "id": "villa-for-sale-ras-al-khaimah-mina-al-arab-marbella-marbella-i-villas-2PYbXfgxff6",
    "url": "https://www.propertyfinder.aehttps://www.propertyfinder.ae/en/plp/buy/villa-for-sale-ras-al-khaimah-mina-al-arab-marbella-marbella-i-villas-2PYbXfgxff6.html",
    "title": "~ 18K Mortgage Cashback",
    "type": "",
    "location": "",
    "price": 8500000,
    "beds": 0,
    "baths": 0,
    "sqft": 0,
    "price_sqft": 0,
    "old_price": 850000018,
    "new_price": 8500000,
    "drop_aed": 841500018,
    "drop_pct": 99.0,
    "detected_at": "2026-03-25T17:36:48.282250Z"
  },
  {
    "id": "villa-for-sale-ras-al-khaimah-mina-al-arab-marbella-marbella-ii-villas-16296618",
    "url": "https://www.propertyfinder.aehttps://www.propertyfinder.ae/en/plp/buy/villa-for-sale-ras-al-khaimah-mina-al-arab-marbella-marbella-ii-villas-16296618.html",
    "title": "~ 19K Mortgage Cashback",
    "type": "",
    "location": "",
    "price": 8800000,
    "beds": 0,
    "baths": 0,
    "sqft": 0,
    "price_sqft": 0,
    "old_price": 880000019,
    "new_price": 8800000,
    "drop_aed": 871200019,
    "drop_pct": 99.0,
    "detected_at": "2026-03-25T17:36:48.282368Z"
  },
  {
    "id": "villa-for-sale-ras-al-khaimah-mina-al-arab-malibu-15998021",
    "url": "https://www.propertyfinder.aehttps://www.propertyfinder.ae/en/plp/buy/villa-for-sale-ras-al-khaimah-mina-al-arab-malibu-15998021.html",
    "title": "~ 16K Mortgage Cashback",
    "type": "",
    "location": "",
    "price": 7500000,
    "beds": 0,
    "baths": 0,
    "sqft": 0,
    "price_sqft": 0,
    "old_price": 750000016,
    "new_price": 7500000,
    "drop_aed": 742500016,
    "drop_pct": 99.0,
    "detected_at": "2026-03-25T17:36:48.282451Z"
  },
  {
    "id": "villa-for-sale-ras-al-khaimah-mina-al-arab-marbella-15822129",
    "url": "https://www.propertyfinder.aehttps://www.propertyfinder.ae/en/plp/buy/villa-for-sale-ras-al-khaimah-mina-al-arab-marbella-15822129.html",
    "title": "~ 19K Mortgage Cashback",
    "type": "",
    "location": "",
    "price": 8800000,
    "beds": 0,
    "baths": 0,
    "sqft": 0,
    "price_sqft": 0,
    "old_price": 880000019,
    "new_price": 8800000,
    "drop_aed": 871200019,
    "drop_pct": 99.0,
    "detected_at": "2026-03-25T17:36:48.282476Z"
  },
  {
    "id": "villa-for-sale-ras-al-khaimah-mina-al-arab-malibu-2Q5kGprpveK",
    "url": "https://www.propertyfinder.aehttps://www.propertyfinder.ae/en/plp/buy/villa-for-sale-ras-al-khaimah-mina-al-arab-malibu-2Q5kGprpveK.html",
    "title": "~ 12K Mortgage Cashback",
    "type": "",
    "location": "",
    "price": 5700000,
    "beds": 0,
    "baths": 0,
    "sqft": 0,
    "price_sqft": 0,
    "old_price": 570000012,
    "new_price": 5700000,
    "drop_aed": 564300012,
    "drop_pct": 99.0,
    "detected_at": "2026-03-25T17:36:48.282502Z"
  },
  {
    "id": "villa-for-sale-ras-al-khaimah-mina-al-arab-marbella-marbella-ii-villas-15632196",
    "url": "https://www.propertyfinder.aehttps://www.propertyfinder.ae/en/plp/buy/villa-for-sale-ras-al-khaimah-mina-al-arab-marbella-marbella-ii-villas-15632196.html",
    "title": "~ 15K Mortgage Cashback",
    "type": "",
    "location": "",
    "price": 6999999,
    "beds": 0,
    "baths": 0,
    "sqft": 0,
    "price_sqft": 0,
    "old_price": 699999915,
    "new_price": 6999999,
    "drop_aed": 692999916,
    "drop_pct": 99.0,
    "detected_at": "2026-03-25T17:36:48.282601Z"
  },
  {
    "id": "villa-for-sale-ras-al-khaimah-mina-al-arab-marbella-marbella-i-villas-15756530",
    "url": "https://www.propertyfinder.aehttps://www.propertyfinder.ae/en/plp/buy/villa-for-sale-ras-al-khaimah-mina-al-arab-marbella-marbella-i-villas-15756530.html",
    "title": "~ 19K Mortgage Cashback",
    "type": "",
    "location": "",
    "price": 9000000,
    "beds": 0,
    "baths": 0,
    "sqft": 0,
    "price_sqft": 0,
    "old_price": 900000019,
    "new_price": 9000000,
    "drop_aed": 891000019,
    "drop_pct": 99.0,
    "detected_at": "2026-03-25T17:36:48.282676Z"
  },
  {
    "id": "villa-for-sale-ras-al-khaimah-mina-al-arab-marbella-14598439",
    "url": "https://www.propertyfinder.aehttps://www.propertyfinder.ae/en/plp/buy/villa-for-sale-ras-al-khaimah-mina-al-arab-marbella-14598439.html",
    "title": "~ 14K Mortgage Cashback",
    "type": "",
    "location": "",
    "price": 6350000,
    "beds": 0,
    "baths": 0,
    "sqft": 0,
    "price_sqft": 0,
    "old_price": 635000014,
    "new_price": 6350000,
    "drop_aed": 628650014,
    "drop_pct": 99.0,
    "detected_at": "2026-03-25T17:36:48.282802Z"
  },
  {
    "id": "apartment-for-sale-ras-al-khaimah-mina-al-arab-hayat-island-bay-residences-2PrhnBkLeeO",
    "url": "https://www.propertyfinder.aehttps://www.propertyfinder.ae/en/plp/buy/apartment-for-sale-ras-al-khaimah-mina-al-arab-hayat-island-bay-residences-2PrhnBkLeeO.html",
    "title": "~ 16K Mortgage Cashback",
    "type": "",
    "location": "",
    "price": 7200000,
    "beds": 0,
    "baths": 0,
    "sqft": 0,
    "price_sqft": 0,
    "old_price": 720000016,
    "new_price": 7200000,
    "drop_aed": 712800016,
    "drop_pct": 99.0,
    "detected_at": "2026-03-25T17:36:48.282825Z"
  },
  {
    "id": "apartment-for-sale-ras-al-khaimah-mina-al-arab-hayat-island-bay-residences-2PeiOeSNtTM",
    "url": "https://www.propertyfinder.aehttps://www.propertyfinder.ae/en/plp/buy/apartment-for-sale-ras-al-khaimah-mina-al-arab-hayat-island-bay-residences-2PeiOeSNtTM.html",
    "title": "Brand New 1BR | High Floor | Beach Access | Vacant",
    "type": "",
    "location": "",
    "price": 1299999,
    "beds": 0,
    "baths": 0,
    "sqft": 0,
    "price_sqft": 0,
    "old_price": 1550000,
    "new_price": 1299999,
    "drop_aed": 250001,
    "drop_pct": 16.1,
    "detected_at": "2026-03-25T17:36:48.282690Z"
  },
  {
    "id": "townhouse-for-sale-ras-al-khaimah-mina-al-arab-flamingo-villas-2PUY4DpLgcz",
    "url": "https://www.propertyfinder.aehttps://www.propertyfinder.ae/en/plp/buy/townhouse-for-sale-ras-al-khaimah-mina-al-arab-flamingo-villas-2PUY4DpLgcz.html",
    "title": "Premier Residential Community | Investor Deal",
    "type": "",
    "location": "",
    "price": 2000000,
    "beds": 0,
    "baths": 0,
    "sqft": 0,
    "price_sqft": 0,
    "old_price": 2300000,
    "new_price": 2000000,
    "drop_aed": 300000,
    "drop_pct": 13.0,
    "detected_at": "2026-03-25T17:36:48.280822Z"
  },
  {
    "id": "apartment-for-sale-ras-al-khaimah-mina-al-arab-hayat-island-bayviews-2Q46IWjPoRc",
    "url": "https://www.propertyfinder.aehttps://www.propertyfinder.ae/en/plp/buy/apartment-for-sale-ras-al-khaimah-mina-al-arab-hayat-island-bayviews-2Q46IWjPoRc.html",
    "title": "High Floor | PHPP till 2029 | High ROI",
    "type": "",
    "location": "",
    "price": 1200000,
    "beds": 0,
    "baths": 0,
    "sqft": 0,
    "price_sqft": 0,
    "old_price": 1300000,
    "new_price": 1200000,
    "drop_aed": 100000,
    "drop_pct": 7.7,
    "detected_at": "2026-03-25T17:36:48.280757Z"
  },
  {
    "id": "apartment-for-sale-ras-al-khaimah-mina-al-arab-hayat-island-bay-residences-2Q30JygnCEK",
    "url": "https://www.propertyfinder.aehttps://www.propertyfinder.ae/en/plp/buy/apartment-for-sale-ras-al-khaimah-mina-al-arab-hayat-island-bay-residences-2Q30JygnCEK.html",
    "title": "Sunset side I Middle floor I Vacant",
    "type": "",
    "location": "",
    "price": 1090000,
    "beds": 0,
    "baths": 0,
    "sqft": 0,
    "price_sqft": 0,
    "old_price": 1170000,
    "new_price": 1090000,
    "drop_aed": 80000,
    "drop_pct": 6.8,
    "detected_at": "2026-03-25T17:36:48.280766Z"
  },
  {
    "id": "apartment-for-sale-ras-al-khaimah-mina-al-arab-cape-hayat-16286550",
    "url": "https://www.propertyfinder.aehttps://www.propertyfinder.ae/en/plp/buy/apartment-for-sale-ras-al-khaimah-mina-al-arab-cape-hayat-16286550.html",
    "title": "Stunning Lagoon View | Prime Investment Deal",
    "type": "",
    "location": "",
    "price": 1400000,
    "beds": 0,
    "baths": 0,
    "sqft": 0,
    "price_sqft": 0,
    "old_price": 1500000,
    "new_price": 1400000,
    "drop_aed": 100000,
    "drop_pct": 6.7,
    "detected_at": "2026-03-25T17:36:48.280965Z"
  },
  {
    "id": "apartment-for-sale-ras-al-khaimah-mina-al-arab-hayat-island-quattro-del-mar-13948224",
    "url": "https://www.propertyfinder.aehttps://www.propertyfinder.ae/en/plp/buy/apartment-for-sale-ras-al-khaimah-mina-al-arab-hayat-island-quattro-del-mar-13948224.html",
    "title": "Studio for Sale on Hayat Island Mina Arab - Luxury Living",
    "type": "",
    "location": "",
    "price": 999999,
    "beds": 0,
    "baths": 0,
    "sqft": 0,
    "price_sqft": 0,
    "old_price": 1070000,
    "new_price": 999999,
    "drop_aed": 70001,
    "drop_pct": 6.5,
    "detected_at": "2026-03-25T17:36:48.282785Z"
  },
  {
    "id": "villa-for-sale-ras-al-khaimah-mina-al-arab-malibu-2Q50ivUsHuS",
    "url": "https://www.propertyfinder.aehttps://www.propertyfinder.ae/en/plp/buy/villa-for-sale-ras-al-khaimah-mina-al-arab-malibu-2Q50ivUsHuS.html",
    "title": "HOT DEAL| FULLY UPGRADED| 3BR VILLA| FOR SALE",
    "type": "",
    "location": "",
    "price": 3200000,
    "beds": 0,
    "baths": 0,
    "sqft": 0,
    "price_sqft": 0,
    "old_price": 3400000,
    "new_price": 3200000,
    "drop_aed": 200000,
    "drop_pct": 5.9,
    "detected_at": "2026-03-25T17:36:48.280770Z"
  },
  {
    "id": "apartment-for-sale-ras-al-khaimah-mina-al-arab-cape-hayat-15269362",
    "url": "https://www.propertyfinder.aehttps://www.propertyfinder.ae/en/plp/buy/apartment-for-sale-ras-al-khaimah-mina-al-arab-cape-hayat-15269362.html",
    "title": "Full Lagoon view | 19th Floor | Hot Deal",
    "type": "",
    "location": "",
    "price": 795000,
    "beds": 0,
    "baths": 0,
    "sqft": 0,
    "price_sqft": 0,
    "old_price": 840000,
    "new_price": 795000,
    "drop_aed": 45000,
    "drop_pct": 5.4,
    "detected_at": "2026-03-25T17:36:48.282137Z"
  },
  {
    "id": "apartment-for-sale-ras-al-khaimah-mina-al-arab-cape-hayat-15269087",
    "url": "https://www.propertyfinder.aehttps://www.propertyfinder.ae/en/plp/buy/apartment-for-sale-ras-al-khaimah-mina-al-arab-cape-hayat-15269087.html",
    "title": "Full Lagoon View- High Floor | 10 Minutes to WYNN",
    "type": "",
    "location": "",
    "price": 755000,
    "beds": 0,
    "baths": 0,
    "sqft": 0,
    "price_sqft": 0,
    "old_price": 795000,
    "new_price": 755000,
    "drop_aed": 40000,
    "drop_pct": 5.0,
    "detected_at": "2026-03-25T17:36:48.282134Z"
  },
  {
    "id": "apartment-for-sale-ras-al-khaimah-mina-al-arab-gateway-residences-2-15910843",
    "url": "https://www.propertyfinder.aehttps://www.propertyfinder.ae/en/plp/buy/apartment-for-sale-ras-al-khaimah-mina-al-arab-gateway-residences-2-15910843.html",
    "title": "hot deal below market price 1 BR lagoon view",
    "type": "",
    "location": "",
    "price": 1025000,
    "beds": 0,
    "baths": 0,
    "sqft": 0,
    "price_sqft": 0,
    "old_price": 1075000,
    "new_price": 1025000,
    "drop_aed": 50000,
    "drop_pct": 4.7,
    "detected_at": "2026-03-25T17:36:48.281217Z"
  },
  {
    "id": "townhouse-for-sale-ras-al-khaimah-mina-al-arab-flamingo-villas-2Putjz2jn1c",
    "url": "https://www.propertyfinder.aehttps://www.propertyfinder.ae/en/plp/buy/townhouse-for-sale-ras-al-khaimah-mina-al-arab-flamingo-villas-2Putjz2jn1c.html",
    "title": "Beautiful 3 Bedroom Flamingo Townhouse",
    "type": "",
    "location": "",
    "price": 2500000,
    "beds": 0,
    "baths": 0,
    "sqft": 0,
    "price_sqft": 0,
    "old_price": 2600000,
    "new_price": 2500000,
    "drop_aed": 100000,
    "drop_pct": 3.8,
    "detected_at": "2026-03-25T17:36:48.280726Z"
  },
  {
    "id": "townhouse-for-sale-ras-al-khaimah-mina-al-arab-marbella-marbella-ii-villas-2Pg9gQOqv68",
    "url": "https://www.propertyfinder.aehttps://www.propertyfinder.ae/en/plp/buy/townhouse-for-sale-ras-al-khaimah-mina-al-arab-marbella-marbella-ii-villas-2Pg9gQOqv68.html",
    "title": "Unbeatable Deal | Brand-New |Steps from the Beach",
    "type": "",
    "location": "",
    "price": 2600000,
    "beds": 0,
    "baths": 0,
    "sqft": 0,
    "price_sqft": 0,
    "old_price": 2700000,
    "new_price": 2600000,
    "drop_aed": 100000,
    "drop_pct": 3.7,
    "detected_at": "2026-03-25T17:36:48.280819Z"
  },
  {
    "id": "townhouse-for-sale-ras-al-khaimah-mina-al-arab-marbella-marbella-ii-villas-2Q1coupmSgq",
    "url": "https://www.propertyfinder.aehttps://www.propertyfinder.ae/en/plp/buy/townhouse-for-sale-ras-al-khaimah-mina-al-arab-marbella-marbella-ii-villas-2Q1coupmSgq.html",
    "title": "Brand New Fully Furnished 2 Beds + Maid | Marbella",
    "type": "",
    "location": "",
    "price": 2650000,
    "beds": 0,
    "baths": 0,
    "sqft": 0,
    "price_sqft": 0,
    "old_price": 2750000,
    "new_price": 2650000,
    "drop_aed": 100000,
    "drop_pct": 3.6,
    "detected_at": "2026-03-25T17:36:48.281253Z"
  },
  {
    "id": "apartment-for-sale-ras-al-khaimah-mina-al-arab-cape-hayat-16310758",
    "url": "https://www.propertyfinder.aehttps://www.propertyfinder.ae/en/plp/buy/apartment-for-sale-ras-al-khaimah-mina-al-arab-cape-hayat-16310758.html",
    "title": "Cosy Studio Apartment on 16th Floor |Handover 2026",
    "type": "",
    "location": "",
    "price": 675000,
    "beds": 0,
    "baths": 0,
    "sqft": 0,
    "price_sqft": 0,
    "old_price": 699000,
    "new_price": 675000,
    "drop_aed": 24000,
    "drop_pct": 3.4,
    "detected_at": "2026-03-25T17:36:48.281849Z"
  },
  {
    "id": "apartment-for-sale-ras-al-khaimah-mina-al-arab-hayat-island-bay-residences-2PeFmiJHIbQ",
    "url": "https://www.propertyfinder.aehttps://www.propertyfinder.ae/en/plp/buy/apartment-for-sale-ras-al-khaimah-mina-al-arab-hayat-island-bay-residences-2PeFmiJHIbQ.html",
    "title": "2 Bedroom for Sale Mina Al Arab - Lagoon View - Luxury Lifestyle",
    "type": "",
    "location": "",
    "price": 2050000,
    "beds": 0,
    "baths": 0,
    "sqft": 0,
    "price_sqft": 0,
    "old_price": 2100000,
    "new_price": 2050000,
    "drop_aed": 50000,
    "drop_pct": 2.4,
    "detected_at": "2026-03-25T17:36:48.281260Z"
  },
  {
    "id": "apartment-for-sale-ras-al-khaimah-mina-al-arab-cape-hayat-2Q1eDMzmmlE",
    "url": "https://www.propertyfinder.aehttps://www.propertyfinder.ae/en/plp/buy/apartment-for-sale-ras-al-khaimah-mina-al-arab-cape-hayat-2Q1eDMzmmlE.html",
    "title": "1 Bedroom Apartment For Sale in Mina - Handover soon",
    "type": "",
    "location": "",
    "price": 1270000,
    "beds": 0,
    "baths": 0,
    "sqft": 0,
    "price_sqft": 0,
    "old_price": 1300000,
    "new_price": 1270000,
    "drop_aed": 30000,
    "drop_pct": 2.3,
    "detected_at": "2026-03-25T17:36:48.281817Z"
  },
  {
    "id": "villa-for-sale-ras-al-khaimah-mina-al-arab-malibu-2PULdPOm3zE",
    "url": "https://www.propertyfinder.aehttps://www.propertyfinder.ae/en/plp/buy/villa-for-sale-ras-al-khaimah-mina-al-arab-malibu-2PULdPOm3zE.html",
    "title": "Malibu Living - 3 Bedroom + Study + Maids",
    "type": "",
    "location": "",
    "price": 3150000,
    "beds": 0,
    "baths": 0,
    "sqft": 0,
    "price_sqft": 0,
    "old_price": 3200000,
    "new_price": 3150000,
    "drop_aed": 50000,
    "drop_pct": 1.6,
    "detected_at": "2026-03-25T17:36:48.280987Z"
  },
  {
    "id": "apartment-for-sale-ras-al-khaimah-mina-al-arab-cape-hayat-2PjOhqFZYMC",
    "url": "https://www.propertyfinder.aehttps://www.propertyfinder.ae/en/plp/buy/apartment-for-sale-ras-al-khaimah-mina-al-arab-cape-hayat-2PjOhqFZYMC.html",
    "title": "Cape Hayat 1-BR with Lagoon View  | Resale",
    "type": "",
    "location": "",
    "price": 1421000,
    "beds": 0,
    "baths": 0,
    "sqft": 0,
    "price_sqft": 0,
    "old_price": 1435000,
    "new_price": 1421000,
    "drop_aed": 14000,
    "drop_pct": 1.0,
    "detected_at": "2026-03-25T17:36:48.281948Z"
  }
]